MANIFEST.in
README.md
requirements.txt
setup.cfg
setup.py
doppelganger/__init__.py
doppelganger/accuracy.py
doppelganger/allocation.py
doppelganger/bayesnets.py
doppelganger/config.py
doppelganger/datasource.py
doppelganger/inputs.py
doppelganger/listbalancer.py
doppelganger/marginals.py
doppelganger/populationgen.py
doppelganger/preprocessing.py
doppelganger.egg-info/PKG-INFO
doppelganger.egg-info/SOURCES.txt
doppelganger.egg-info/dependency_links.txt
doppelganger.egg-info/requires.txt
doppelganger.egg-info/top_level.txt
test/test_accuracy.py
test/test_allocation.py
test/test_bayes_net.py
test/test_config.py
test/test_datasource.py
test/test_download_allocate_generate.py
test/test_fetch_pums_data_from_db.py
test/test_generation.py
test/test_inputs.py
test/test_listbalancer.py
test/test_marginals.py
test/test_preprocessing.py