Metadata-Version: 1.0
Name: doppelganger
Version: 0.1.4
Summary: Population synthesis library
Home-page: UNKNOWN
Author: Kat Busch, Kael Greco and contributors
Author-email: doppelganger@sidewalklabs.com
License: UNKNOWN
Platform: UNKNOWN
